fogbugz.py
fogbugz-1.0.6.dist-info/DESCRIPTION.rst
fogbugz-1.0.6.dist-info/METADATA
fogbugz-1.0.6.dist-info/RECORD
fogbugz-1.0.6.dist-info/WHEEL
fogbugz-1.0.6.dist-info/metadata.json
fogbugz-1.0.6.dist-info/top_level.txt
