Metadata-Version: 2.0
Name: fogbugz
Version: 1.0.6
Summary: Python library for interacting with the FogBugz API
Home-page: https://github.com/yougov/FogBugzPy
Author: YouGov, Plc.
Author-email: open-source@yougov.com
License: Copyright (c) 2011, Fog Creek Software, Inc.
Requires-Dist: BeautifulSoup4
Requires-Dist: lxml
Requires-Dist: six
